{"2017-04-21": {"John Wick: Chapter 2": {"time": "05:17", "provider": "Paramount", "rev": "9.00"}}, "2017-04-16": {"Now You See Me": {"time": "19:59", "provider": "Sony Pictures", "rev": "5.00"}}, "stb": "stb8", "2017-04-06": {"Chappie": {"time": "12:40", "provider": "Lionsgate", "rev": "1.00"}}, "2017-04-09": {"Harry Potter and the Deathly Hallows: Part 2": {"time": "19:16", "provider": "Lionsgate", "rev": "8.00"}, "Tomorrow Everything Starts": {"time": "04:32", "provider": "Miramax", "rev": "10.00"}}, "2017-04-08": {"Pirates of the Caribbean: Dead Men Tell No Tales": {"time": "13:06", "provider": "Paramount", "rev": "1.00"}}, "2017-04-19": {"Dogtooth": {"time": "21:23", "provider": "MGM", "rev": "7.00"}}, "2017-04-12": {"Fifty Shades Darker": {"time": "13:53", "provider": "Sony Pictures", "rev": "4.00"}}}